{
    "description": "",
    "tags": [
        {
            "id": 11013591,
            "tagId": 26739,
            "name": "weather",
            "value": "clear",
            "labelerLogin": "inbox@datasetninja.com",
            "createdAt": "2023-11-24T22:07:06.205Z",
            "updatedAt": "2023-11-24T22:07:06.205Z"
        },
        {
            "id": 11013592,
            "tagId": 26740,
            "name": "scene",
            "value": "city street",
            "labelerLogin": "inbox@datasetninja.com",
            "createdAt": "2023-11-24T22:07:06.205Z",
            "updatedAt": "2023-11-24T22:07:06.205Z"
        },
        {
            "id": 11013593,
            "tagId": 26741,
            "name": "timeofday",
            "value": "daytime",
            "labelerLogin": "inbox@datasetninja.com",
            "createdAt": "2023-11-24T22:07:06.205Z",
            "updatedAt": "2023-11-24T22:07:06.205Z"
        }
    ],
    "size": {
        "height": 720,
        "width": 1280
    },
    "objects": [
        {
            "id": 91418840,
            "classId": 6508800,
            "description": "",
            "geometryType": "rectangle",
            "labelerLogin": "inbox@datasetninja.com",
            "createdAt": "2023-11-24T22:07:06.215Z",
            "updatedAt": "2023-11-24T22:07:06.215Z",
            "tags": [
                {
                    "id": 75662498,
                    "tagId": 26742,
                    "name": "attributes",
                    "value": "{'occluded': True, 'truncated': False, 'trafficLightColor': 'none'}",
                    "labelerLogin": "inbox@datasetninja.com",
                    "createdAt": "2023-11-24T22:07:06.215Z",
                    "updatedAt": "2023-11-24T22:07:06.215Z"
                }
            ],
            "classTitle": "car",
            "points": {
                "exterior": [
                    [
                        554,
                        327
                    ],
                    [
                        564,
                        338
                    ]
                ],
                "interior": []
            }
        },
        {
            "id": 91418839,
            "classId": 6508800,
            "description": "",
            "geometryType": "rectangle",
            "labelerLogin": "inbox@datasetninja.com",
            "createdAt": "2023-11-24T22:07:06.214Z",
            "updatedAt": "2023-11-24T22:07:06.214Z",
            "tags": [
                {
                    "id": 75662497,
                    "tagId": 26742,
                    "name": "attributes",
                    "value": "{'occluded': True, 'truncated': False, 'trafficLightColor': 'none'}",
                    "labelerLogin": "inbox@datasetninja.com",
                    "createdAt": "2023-11-24T22:07:06.214Z",
                    "updatedAt": "2023-11-24T22:07:06.214Z"
                }
            ],
            "classTitle": "car",
            "points": {
                "exterior": [
                    [
                        605,
                        321
                    ],
                    [
                        617,
                        332
                    ]
                ],
                "interior": []
            }
        },
        {
            "id": 91418838,
            "classId": 6508800,
            "description": "",
            "geometryType": "rectangle",
            "labelerLogin": "inbox@datasetninja.com",
            "createdAt": "2023-11-24T22:07:06.214Z",
            "updatedAt": "2023-11-24T22:07:06.214Z",
            "tags": [
                {
                    "id": 75662496,
                    "tagId": 26742,
                    "name": "attributes",
                    "value": "{'occluded': False, 'truncated': False, 'trafficLightColor': 'none'}",
                    "labelerLogin": "inbox@datasetninja.com",
                    "createdAt": "2023-11-24T22:07:06.213Z",
                    "updatedAt": "2023-11-24T22:07:06.213Z"
                }
            ],
            "classTitle": "car",
            "points": {
                "exterior": [
                    [
                        615,
                        329
                    ],
                    [
                        628,
                        341
                    ]
                ],
                "interior": []
            }
        },
        {
            "id": 91418837,
            "classId": 6508800,
            "description": "",
            "geometryType": "rectangle",
            "labelerLogin": "inbox@datasetninja.com",
            "createdAt": "2023-11-24T22:07:06.213Z",
            "updatedAt": "2023-11-24T22:07:06.213Z",
            "tags": [
                {
                    "id": 75662495,
                    "tagId": 26742,
                    "name": "attributes",
                    "value": "{'occluded': False, 'truncated': False, 'trafficLightColor': 'none'}",
                    "labelerLogin": "inbox@datasetninja.com",
                    "createdAt": "2023-11-24T22:07:06.213Z",
                    "updatedAt": "2023-11-24T22:07:06.213Z"
                }
            ],
            "classTitle": "car",
            "points": {
                "exterior": [
                    [
                        538,
                        328
                    ],
                    [
                        555,
                        343
                    ]
                ],
                "interior": []
            }
        },
        {
            "id": 91418836,
            "classId": 6508800,
            "description": "",
            "geometryType": "rectangle",
            "labelerLogin": "inbox@datasetninja.com",
            "createdAt": "2023-11-24T22:07:06.213Z",
            "updatedAt": "2023-11-24T22:07:06.213Z",
            "tags": [
                {
                    "id": 75662494,
                    "tagId": 26742,
                    "name": "attributes",
                    "value": "{'occluded': False, 'truncated': False, 'trafficLightColor': 'none'}",
                    "labelerLogin": "inbox@datasetninja.com",
                    "createdAt": "2023-11-24T22:07:06.213Z",
                    "updatedAt": "2023-11-24T22:07:06.213Z"
                }
            ],
            "classTitle": "car",
            "points": {
                "exterior": [
                    [
                        566,
                        333
                    ],
                    [
                        580,
                        344
                    ]
                ],
                "interior": []
            }
        },
        {
            "id": 91418835,
            "classId": 6508800,
            "description": "",
            "geometryType": "rectangle",
            "labelerLogin": "inbox@datasetninja.com",
            "createdAt": "2023-11-24T22:07:06.213Z",
            "updatedAt": "2023-11-24T22:07:06.213Z",
            "tags": [
                {
                    "id": 75662493,
                    "tagId": 26742,
                    "name": "attributes",
                    "value": "{'occluded': False, 'truncated': False, 'trafficLightColor': 'none'}",
                    "labelerLogin": "inbox@datasetninja.com",
                    "createdAt": "2023-11-24T22:07:06.213Z",
                    "updatedAt": "2023-11-24T22:07:06.213Z"
                }
            ],
            "classTitle": "car",
            "points": {
                "exterior": [
                    [
                        645,
                        343
                    ],
                    [
                        685,
                        373
                    ]
                ],
                "interior": []
            }
        },
        {
            "id": 91418834,
            "classId": 6508800,
            "description": "",
            "geometryType": "rectangle",
            "labelerLogin": "inbox@datasetninja.com",
            "createdAt": "2023-11-24T22:07:06.212Z",
            "updatedAt": "2023-11-24T22:07:06.212Z",
            "tags": [
                {
                    "id": 75662492,
                    "tagId": 26742,
                    "name": "attributes",
                    "value": "{'occluded': False, 'truncated': False, 'trafficLightColor': 'none'}",
                    "labelerLogin": "inbox@datasetninja.com",
                    "createdAt": "2023-11-24T22:07:06.212Z",
                    "updatedAt": "2023-11-24T22:07:06.212Z"
                }
            ],
            "classTitle": "car",
            "points": {
                "exterior": [
                    [
                        74,
                        352
                    ],
                    [
                        271,
                        458
                    ]
                ],
                "interior": []
            }
        },
        {
            "id": 91418833,
            "classId": 6508800,
            "description": "",
            "geometryType": "rectangle",
            "labelerLogin": "inbox@datasetninja.com",
            "createdAt": "2023-11-24T22:07:06.212Z",
            "updatedAt": "2023-11-24T22:07:06.212Z",
            "tags": [
                {
                    "id": 75662491,
                    "tagId": 26742,
                    "name": "attributes",
                    "value": "{'occluded': True, 'truncated': False, 'trafficLightColor': 'none'}",
                    "labelerLogin": "inbox@datasetninja.com",
                    "createdAt": "2023-11-24T22:07:06.212Z",
                    "updatedAt": "2023-11-24T22:07:06.212Z"
                }
            ],
            "classTitle": "car",
            "points": {
                "exterior": [
                    [
                        456,
                        342
                    ],
                    [
                        486,
                        380
                    ]
                ],
                "interior": []
            }
        },
        {
            "id": 91418832,
            "classId": 6508800,
            "description": "",
            "geometryType": "rectangle",
            "labelerLogin": "inbox@datasetninja.com",
            "createdAt": "2023-11-24T22:07:06.210Z",
            "updatedAt": "2023-11-24T22:07:06.210Z",
            "tags": [
                {
                    "id": 75662490,
                    "tagId": 26742,
                    "name": "attributes",
                    "value": "{'occluded': True, 'truncated': False, 'trafficLightColor': 'none'}",
                    "labelerLogin": "inbox@datasetninja.com",
                    "createdAt": "2023-11-24T22:07:06.210Z",
                    "updatedAt": "2023-11-24T22:07:06.210Z"
                }
            ],
            "classTitle": "car",
            "points": {
                "exterior": [
                    [
                        405,
                        343
                    ],
                    [
                        464,
                        388
                    ]
                ],
                "interior": []
            }
        },
        {
            "id": 91418831,
            "classId": 6508800,
            "description": "",
            "geometryType": "rectangle",
            "labelerLogin": "inbox@datasetninja.com",
            "createdAt": "2023-11-24T22:07:06.209Z",
            "updatedAt": "2023-11-24T22:07:06.209Z",
            "tags": [
                {
                    "id": 75662489,
                    "tagId": 26742,
                    "name": "attributes",
                    "value": "{'occluded': True, 'truncated': False, 'trafficLightColor': 'none'}",
                    "labelerLogin": "inbox@datasetninja.com",
                    "createdAt": "2023-11-24T22:07:06.209Z",
                    "updatedAt": "2023-11-24T22:07:06.209Z"
                }
            ],
            "classTitle": "car",
            "points": {
                "exterior": [
                    [
                        712,
                        333
                    ],
                    [
                        814,
                        414
                    ]
                ],
                "interior": []
            }
        },
        {
            "id": 91418830,
            "classId": 6508800,
            "description": "",
            "geometryType": "rectangle",
            "labelerLogin": "inbox@datasetninja.com",
            "createdAt": "2023-11-24T22:07:06.209Z",
            "updatedAt": "2023-11-24T22:07:06.209Z",
            "tags": [
                {
                    "id": 75662488,
                    "tagId": 26742,
                    "name": "attributes",
                    "value": "{'occluded': False, 'truncated': False, 'trafficLightColor': 'none'}",
                    "labelerLogin": "inbox@datasetninja.com",
                    "createdAt": "2023-11-24T22:07:06.209Z",
                    "updatedAt": "2023-11-24T22:07:06.209Z"
                }
            ],
            "classTitle": "car",
            "points": {
                "exterior": [
                    [
                        783,
                        334
                    ],
                    [
                        987,
                        457
                    ]
                ],
                "interior": []
            }
        },
        {
            "id": 91418829,
            "classId": 6508806,
            "description": "",
            "geometryType": "rectangle",
            "labelerLogin": "inbox@datasetninja.com",
            "createdAt": "2023-11-24T22:07:06.209Z",
            "updatedAt": "2023-11-24T22:07:06.209Z",
            "tags": [
                {
                    "id": 75662487,
                    "tagId": 26742,
                    "name": "attributes",
                    "value": "{'occluded': False, 'truncated': False, 'trafficLightColor': 'none'}",
                    "labelerLogin": "inbox@datasetninja.com",
                    "createdAt": "2023-11-24T22:07:06.208Z",
                    "updatedAt": "2023-11-24T22:07:06.208Z"
                }
            ],
            "classTitle": "person",
            "points": {
                "exterior": [
                    [
                        503,
                        342
                    ],
                    [
                        516,
                        375
                    ]
                ],
                "interior": []
            }
        },
        {
            "id": 91418828,
            "classId": 6508800,
            "description": "",
            "geometryType": "rectangle",
            "labelerLogin": "inbox@datasetninja.com",
            "createdAt": "2023-11-24T22:07:06.208Z",
            "updatedAt": "2023-11-24T22:07:06.208Z",
            "tags": [
                {
                    "id": 75662486,
                    "tagId": 26742,
                    "name": "attributes",
                    "value": "{'occluded': False, 'truncated': False, 'trafficLightColor': 'none'}",
                    "labelerLogin": "inbox@datasetninja.com",
                    "createdAt": "2023-11-24T22:07:06.208Z",
                    "updatedAt": "2023-11-24T22:07:06.208Z"
                }
            ],
            "classTitle": "car",
            "points": {
                "exterior": [
                    [
                        495,
                        347
                    ],
                    [
                        528,
                        367
                    ]
                ],
                "interior": []
            }
        },
        {
            "id": 91418827,
            "classId": 6508800,
            "description": "",
            "geometryType": "rectangle",
            "labelerLogin": "inbox@datasetninja.com",
            "createdAt": "2023-11-24T22:07:06.207Z",
            "updatedAt": "2023-11-24T22:07:06.207Z",
            "tags": [
                {
                    "id": 75662485,
                    "tagId": 26742,
                    "name": "attributes",
                    "value": "{'occluded': False, 'truncated': False, 'trafficLightColor': 'none'}",
                    "labelerLogin": "inbox@datasetninja.com",
                    "createdAt": "2023-11-24T22:07:06.207Z",
                    "updatedAt": "2023-11-24T22:07:06.207Z"
                }
            ],
            "classTitle": "car",
            "points": {
                "exterior": [
                    [
                        573,
                        315
                    ],
                    [
                        599,
                        329
                    ]
                ],
                "interior": []
            }
        },
        {
            "id": 91418826,
            "classId": 6508802,
            "description": "",
            "geometryType": "polygon",
            "labelerLogin": "inbox@datasetninja.com",
            "createdAt": "2023-11-24T22:07:06.207Z",
            "updatedAt": "2023-11-24T22:07:06.207Z",
            "tags": [
                {
                    "id": 75662484,
                    "tagId": 26742,
                    "name": "attributes",
                    "value": "{'areaType': 'direct'}",
                    "labelerLogin": "inbox@datasetninja.com",
                    "createdAt": "2023-11-24T22:07:06.206Z",
                    "updatedAt": "2023-11-24T22:07:06.206Z"
                }
            ],
            "classTitle": "drivable area",
            "points": {
                "exterior": [
                    [
                        618,
                        353
                    ],
                    [
                        816,
                        473
                    ],
                    [
                        994,
                        464
                    ],
                    [
                        1279,
                        552
                    ],
                    [
                        1279,
                        719
                    ],
                    [
                        1252,
                        719
                    ],
                    [
                        1055,
                        712
                    ],
                    [
                        696,
                        673
                    ],
                    [
                        346,
                        719
                    ],
                    [
                        0,
                        719
                    ],
                    [
                        0,
                        567
                    ],
                    [
                        578,
                        353
                    ]
                ],
                "interior": []
            }
        },
        {
            "id": 91418825,
            "classId": 6508803,
            "description": "",
            "geometryType": "line",
            "labelerLogin": "inbox@datasetninja.com",
            "createdAt": "2023-11-24T22:07:06.206Z",
            "updatedAt": "2023-11-24T22:07:06.206Z",
            "tags": [
                {
                    "id": 75662483,
                    "tagId": 26742,
                    "name": "attributes",
                    "value": "{'laneDirection': 'vertical', 'laneStyle': 'dashed', 'laneType': 'crosswalk'}",
                    "labelerLogin": "inbox@datasetninja.com",
                    "createdAt": "2023-11-24T22:07:06.206Z",
                    "updatedAt": "2023-11-24T22:07:06.206Z"
                }
            ],
            "classTitle": "lane",
            "points": {
                "exterior": [
                    [
                        529,
                        363
                    ],
                    [
                        637,
                        361
                    ]
                ],
                "interior": []
            }
        },
        {
            "id": 91418824,
            "classId": 6508803,
            "description": "",
            "geometryType": "line",
            "labelerLogin": "inbox@datasetninja.com",
            "createdAt": "2023-11-24T22:07:06.206Z",
            "updatedAt": "2023-11-24T22:07:06.206Z",
            "tags": [
                {
                    "id": 75662482,
                    "tagId": 26742,
                    "name": "attributes",
                    "value": "{'laneDirection': 'vertical', 'laneStyle': 'dashed', 'laneType': 'crosswalk'}",
                    "labelerLogin": "inbox@datasetninja.com",
                    "createdAt": "2023-11-24T22:07:06.206Z",
                    "updatedAt": "2023-11-24T22:07:06.206Z"
                }
            ],
            "classTitle": "lane",
            "points": {
                "exterior": [
                    [
                        530,
                        356
                    ],
                    [
                        633,
                        355
                    ]
                ],
                "interior": []
            }
        },
        {
            "id": 91418823,
            "classId": 6508803,
            "description": "",
            "geometryType": "line",
            "labelerLogin": "inbox@datasetninja.com",
            "createdAt": "2023-11-24T22:07:06.206Z",
            "updatedAt": "2023-11-24T22:07:06.206Z",
            "tags": [
                {
                    "id": 75662481,
                    "tagId": 26742,
                    "name": "attributes",
                    "value": "{'laneDirection': 'vertical', 'laneStyle': 'dashed', 'laneType': 'crosswalk'}",
                    "labelerLogin": "inbox@datasetninja.com",
                    "createdAt": "2023-11-24T22:07:06.206Z",
                    "updatedAt": "2023-11-24T22:07:06.206Z"
                }
            ],
            "classTitle": "lane",
            "points": {
                "exterior": [
                    [
                        549,
                        346
                    ],
                    [
                        625,
                        346
                    ]
                ],
                "interior": []
            }
        }
    ]
}